super_productivity_webdav_api/__init__.py
super_productivity_webdav_api/client.py
super_productivity_webdav_api/exceptions.py
super_productivity_webdav_api-0.1.1.dist-info/LICENSE
super_productivity_webdav_api-0.1.1.dist-info/METADATA
super_productivity_webdav_api-0.1.1.dist-info/WHEEL
super_productivity_webdav_api-0.1.1.dist-info/top_level.txt
super_productivity_webdav_api-0.1.1.dist-info/RECORD
