Metadata-Version: 2.1
Name: super_productivity_webdav_api
Version: 0.1.1
Summary: A python API for managing Super Productivity tasks through webdav.
Author-email: Arnoud van Heuvelen <avanheuvelen@pm.me>
License: MIT
Project-URL: homepage, https://github.com/avanheuvelen/super-productivity-webdav-api
Project-URL: repository, https://github.com/avanheuvelen/super-productivity-webdav-api
Project-URL: issues, https://github.com/avanheuvelen/super-productivity-webdav-api/issues
Keywords: webdav,task management,super-productivity
Classifier: Intended Audience :: Developers
Classifier: License :: OSI Approved :: MIT License
Classifier: Programming Language :: Python :: 3
License-File: LICENSE
Requires-Dist: webdav4>=0.10
Requires-Dist: nanoid>=2.0
